tensormesh/__init__.py
tensormesh/cli/__init__.py
tensormesh/cli/__main__.py
tensormesh/cli/benchmark/__init__.py
tensormesh/cli/benchmark/bench.py
tensormesh/cli/benchmark/model_configs.json
tmesh-0.1.15.dist-info/METADATA
tmesh-0.1.15.dist-info/WHEEL
tmesh-0.1.15.dist-info/entry_points.txt
tmesh-0.1.15.dist-info/top_level.txt
tmesh-0.1.15.dist-info/RECORD
