Metadata-Version: 2.4
Name: tmesh
Version: 0.1.15
Summary: TensorMesh CLI tool suite
Classifier: Programming Language :: Python :: 3
Classifier: Operating System :: OS Independent
Requires-Python: >=3.9
Requires-Dist: openai
Requires-Dist: requests
